lalatools/__init__.py
lalatools/DigitalImageProcessing/ImageProcess.py
lalatools/DigitalImageProcessing/__init__.py
lalatools/ManageFileSystem/FileSystem.py
lalatools/ManageFileSystem/__init__.py
lalatools/digital_image_processing/__init__.py
lalatools/digital_image_processing/image_process.py
lalatools/manage_file_system/__init__.py
lalatools/manage_file_system/file_system.py
LalaTools-0.0.11.dist-info/LICENSE.txt
LalaTools-0.0.11.dist-info/METADATA
LalaTools-0.0.11.dist-info/WHEEL
LalaTools-0.0.11.dist-info/top_level.txt
LalaTools-0.0.11.dist-info/RECORD
